{
    "version": "BT15",
    "description": "Inject games into various Wii U VCs.",
    "homepage": "https://github.com/stuff-by-3-random-dudes/UWUVCI-AIO-WPF",
    "license": "GPL-3.0-only",
    "url": "https://github.com/stuff-by-3-random-dudes/UWUVCI-AIO-WPF/releases/download/BT15/UWUVCI.AIO.BT15.Installer.exe",
    "hash": "4d6189c1bd0371c331db433c582baf3d4ff2de814cc467354df25dc4f81c4989",
    "innosetup": true,
    "bin": [
        "UWUVCI AIO.exe",
        "UWUVCI VWII.exe"
    ],
    "shortcuts": [
        [
            "UWUVCI AIO.exe",
            "UWUVCI AIO"
        ],
        [
            "UWUVCI VWII.exe",
            "UWUVCI VWII"
        ]
    ],
    "persist": [
        "InjectedGames",
        "bin\\BaseGames",
        "bin\\keys"
    ],
    "checkver": {
        "url": "https://github.com/stuff-by-3-random-dudes/UWUVCI-AIO-WPF/releases/latest",
        "regex": "UWUVCI.AIO.([A-z\\d.]+).Installer.exe"
    },
    "autoupdate": {
        "url": "https://github.com/stuff-by-3-random-dudes/UWUVCI-AIO-WPF/releases/download/$version/UWUVCI.AIO.$version.Installer.exe"
    }
}
